{
  "generated_at": "2025-08-14T18:58:13.854236+00:00",
  "notes": [],
  "changes": [
    {
      "symbol": "ADA/USDT",
      "timeframe": "1w",
      "diff": {
        "breakout_up": {
          "from": true,
          "to": false
        }
      },
      "price": 0.899775
    },
    {
      "symbol": "ADA/USDT",
      "timeframe": "15m",
      "diff": {
        "long_regime": {
          "from": "above_200",
          "to": "below_200"
        }
      },
      "price": 0.899775
    },
    {
      "symbol": "ADA/USDT",
      "timeframe": "1m",
      "diff": {
        "trend": {
          "from": "trending",
          "to": "choppy"
        },
        "breakout_dn": {
          "from": false,
          "to": true
        },
        "ema_state": {
          "from": "bearish",
          "to": "bullish"
        },
        "ema_alignment": {
          "from": "bearish",
          "to": "mixed"
        },
        "scalp_ema": {
          "from": "bearish",
          "to": "bullish"
        }
      },
      "price": 0.899775
    },
    {
      "symbol": "AI16Z/USDT",
      "timeframe": "5m",
      "diff": {
        "rsi_zone": {
          "from": "oversold",
          "to": "neutral"
        },
        "macd_cross": {
          "from": "bullish",
          "to": "none"
        }
      },
      "price": 0.1226
    },
    {
      "symbol": "AI16Z/USDT",
      "timeframe": "1m",
      "diff": {
        "rsi_zone": {
          "from": "oversold",
          "to": "neutral"
        },
        "ema_state": {
          "from": "bearish",
          "to": "bullish"
        },
        "ema_alignment": {
          "from": "bearish",
          "to": "mixed"
        },
        "scalp_ema": {
          "from": "bearish",
          "to": "bullish"
        }
      },
      "price": 0.1226
    },
    {
      "symbol": "ALGO/USDT",
      "timeframe": "1m",
      "diff": {
        "rsi_zone": {
          "from": "overbought",
          "to": "neutral"
        },
        "trend": {
          "from": "trending",
          "to": "choppy"
        },
        "ema_state": {
          "from": "bullish",
          "to": "bearish"
        },
        "ema_alignment": {
          "from": "mixed",
          "to": "bearish"
        }
      },
      "price": 0.25429
    },
    {
      "symbol": "APE/USDT",
      "timeframe": "4h",
      "diff": {
        "scalp_ema": {
          "from": "bullish",
          "to": "bearish"
        }
      },
      "price": 0.6063
    },
    {
      "symbol": "APE/USDT",
      "timeframe": "1h",
      "diff": {
        "rsi_zone": {
          "from": "neutral",
          "to": "oversold"
        }
      },
      "price": 0.6063
    },
    {
      "symbol": "APE/USDT",
      "timeframe": "1m",
      "diff": {
        "rsi_zone": {
          "from": "oversold",
          "to": "neutral"
        },
        "ema_alignment": {
          "from": "mixed",
          "to": "bearish"
        },
        "long_regime": {
          "from": "above_200",
          "to": "below_200"
        },
        "scalp_ema": {
          "from": "bearish",
          "to": "bullish"
        }
      },
      "price": 0.6063
    },
    {
      "symbol": "ATOM/USDT",
      "timeframe": "15m",
      "diff": {
        "rsi_zone": {
          "from": "oversold",
          "to": "neutral"
        }
      },
      "price": 4.533
    },
    {
      "symbol": "ATOM/USDT",
      "timeframe": "1m",
      "diff": {
        "trend": {
          "from": "trending",
          "to": "choppy"
        },
        "ema_state": {
          "from": "bearish",
          "to": "bullish"
        },
        "ema_alignment": {
          "from": "bearish",
          "to": "mixed"
        }
      },
      "price": 4.533
    },
    {
      "symbol": "AVAX/USDT",
      "timeframe": "5m",
      "diff": {
        "trend": {
          "from": "trending",
          "to": "choppy"
        }
      },
      "price": 23.67
    },
    {
      "symbol": "BCH/USDT",
      "timeframe": "1m",
      "diff": {
        "rsi_zone": {
          "from": "neutral",
          "to": "overbought"
        },
        "breakout_up": {
          "from": false,
          "to": true
        },
        "ema_state": {
          "from": "bullish",
          "to": "bearish"
        },
        "ema_alignment": {
          "from": "mixed",
          "to": "bearish"
        },
        "long_regime": {
          "from": "below_200",
          "to": "above_200"
        },
        "scalp_ema": {
          "from": "bearish",
          "to": "bullish"
        }
      },
      "price": 590.13
    },
    {
      "symbol": "BERA/USDT",
      "timeframe": "5m",
      "diff": {
        "trend": {
          "from": "trending",
          "to": "choppy"
        }
      },
      "price": 2.242
    },
    {
      "symbol": "BERA/USDT",
      "timeframe": "1m",
      "diff": {
        "rsi_zone": {
          "from": "overbought",
          "to": "oversold"
        },
        "ema_state": {
          "from": "bullish",
          "to": "bearish"
        },
        "ema_alignment": {
          "from": "bullish",
          "to": "mixed"
        },
        "scalp_ema": {
          "from": "bullish",
          "to": "bearish"
        }
      },
      "price": 2.242
    },
    {
      "symbol": "BNB/USDT",
      "timeframe": "1m",
      "diff": {
        "rsi_zone": {
          "from": "neutral",
          "to": "overbought"
        },
        "ema_state": {
          "from": "bearish",
          "to": "bullish"
        },
        "ema_alignment": {
          "from": "bearish",
          "to": "mixed"
        },
        "long_regime": {
          "from": "below_200",
          "to": "above_200"
        }
      },
      "price": 839.69
    },
    {
      "symbol": "BTC/USDT",
      "timeframe": "1h",
      "diff": {
        "rsi_zone": {
          "from": "oversold",
          "to": "neutral"
        }
      },
      "price": 118185.9
    },
    {
      "symbol": "BTC/USDT",
      "timeframe": "5m",
      "diff": {
        "trend": {
          "from": "trending",
          "to": "choppy"
        },
        "scalp_ema": {
          "from": "bearish",
          "to": "bullish"
        }
      },
      "price": 118185.9
    },
    {
      "symbol": "BTC/USDT",
      "timeframe": "1m",
      "diff": {
        "ema_state": {
          "from": "bearish",
          "to": "bullish"
        },
        "ema_alignment": {
          "from": "bearish",
          "to": "bullish"
        },
        "long_regime": {
          "from": "below_200",
          "to": "above_200"
        },
        "scalp_ema": {
          "from": "bearish",
          "to": "bullish"
        }
      },
      "price": 118185.9
    },
    {
      "symbol": "CRO/USDT",
      "timeframe": "1h",
      "diff": {
        "rsi_zone": {
          "from": "oversold",
          "to": "neutral"
        }
      },
      "price": 0.15299
    },
    {
      "symbol": "CRO/USDT",
      "timeframe": "15m",
      "diff": {
        "rsi_zone": {
          "from": "oversold",
          "to": "neutral"
        }
      },
      "price": 0.15299
    },
    {
      "symbol": "CRO/USDT",
      "timeframe": "5m",
      "diff": {
        "rsi_zone": {
          "from": "neutral",
          "to": "overbought"
        },
        "breakout_up": {
          "from": true,
          "to": false
        },
        "scalp_ema": {
          "from": "bearish",
          "to": "bullish"
        }
      },
      "price": 0.15299
    },
    {
      "symbol": "CRO/USDT",
      "timeframe": "1m",
      "diff": {
        "ema_alignment": {
          "from": "mixed",
          "to": "bullish"
        },
        "long_regime": {
          "from": "below_200",
          "to": "above_200"
        }
      },
      "price": 0.15299
    },
    {
      "symbol": "DAI/USDT",
      "timeframe": "15m",
      "diff": {
        "trend": {
          "from": "trending",
          "to": "choppy"
        }
      },
      "price": 0.99906
    },
    {
      "symbol": "DOGE/USDT",
      "timeframe": "5m",
      "diff": {
        "trend": {
          "from": "trending",
          "to": "choppy"
        },
        "scalp_ema": {
          "from": "bearish",
          "to": "bullish"
        }
      },
      "price": 0.22449
    },
    {
      "symbol": "DOGE/USDT",
      "timeframe": "1m",
      "diff": {
        "rsi_zone": {
          "from": "oversold",
          "to": "overbought"
        },
        "ema_state": {
          "from": "bearish",
          "to": "bullish"
        },
        "ema_alignment": {
          "from": "bearish",
          "to": "mixed"
        },
        "long_regime": {
          "from": "below_200",
          "to": "above_200"
        },
        "scalp_ema": {
          "from": "bearish",
          "to": "bullish"
        }
      },
      "price": 0.22449
    },
    {
      "symbol": "DOT/USDT",
      "timeframe": "5m",
      "diff": {
        "trend": {
          "from": "trending",
          "to": "choppy"
        },
        "scalp_ema": {
          "from": "bearish",
          "to": "bullish"
        }
      },
      "price": 3.9962
    },
    {
      "symbol": "DOT/USDT",
      "timeframe": "1m",
      "diff": {
        "trend": {
          "from": "choppy",
          "to": "trending"
        },
        "breakout_up": {
          "from": true,
          "to": false
        },
        "long_regime": {
          "from": "below_200",
          "to": "above_200"
        }
      },
      "price": 3.9962
    },
    {
      "symbol": "ETH/USDT",
      "timeframe": "1h",
      "diff": {
        "breakout_dn": {
          "from": true,
          "to": false
        }
      },
      "price": 4550.07
    },
    {
      "symbol": "ETH/USDT",
      "timeframe": "1m",
      "diff": {
        "ema_state": {
          "from": "bearish",
          "to": "bullish"
        },
        "ema_alignment": {
          "from": "bearish",
          "to": "mixed"
        },
        "scalp_ema": {
          "from": "bearish",
          "to": "bullish"
        }
      },
      "price": 4550.07
    }
  ]
}